setup.py
distributions_b01/Binomialdistribution.py
distributions_b01/Gaussiandistribution.py
distributions_b01/Generaldistribution.py
distributions_b01/__init__.py
distributions_b01.egg-info/PKG-INFO
distributions_b01.egg-info/SOURCES.txt
distributions_b01.egg-info/dependency_links.txt
distributions_b01.egg-info/not-zip-safe
distributions_b01.egg-info/top_level.txt