Metadata-Version: 1.0
Name: distributions-b01
Version: 0.1
Summary: Gaussian distributions
Home-page: UNKNOWN
Author: Botha Moseti
Author-email: derrickbotha2@gmail.com
License: UNKNOWN
Platform: UNKNOWN
